nano_prom_exporter/__init__.py
nano_prom_exporter/__main__.py
nano_prom_exporter/config.py
nano_prom_exporter/nanoRPC.py
nano_prom_exporter/nanoStats.py
nano_prom_exporter-0.1.12.dist-info/LICENSE
nano_prom_exporter-0.1.12.dist-info/METADATA
nano_prom_exporter-0.1.12.dist-info/WHEEL
nano_prom_exporter-0.1.12.dist-info/entry_points.txt
nano_prom_exporter-0.1.12.dist-info/top_level.txt
nano_prom_exporter-0.1.12.dist-info/RECORD
