Metadata-Version: 2.1
Name: nano-prom-exporter
Version: 0.1.12
Summary: Export nano_node stats for prometheus
Home-page: https://github.com/nanocurrency/nano_prom_exporter
Author: Russel Waters
Author-email: Russel@nano.org
License: UNKNOWN
Platform: UNKNOWN
Requires-Python: >=3.7
Requires-Dist: requests
Requires-Dist: prometheus-client
Requires-Dist: psutil
